flint.pypy37-pp73-x86_64-linux-gnu.so
flint.cpython-37m-x86_64-linux-gnu.so
flint_py-0.3.7.dist-info/top_level.txt
flint_py-0.3.7.dist-info/METADATA
flint_py-0.3.7.dist-info/RECORD
flint_py-0.3.7.dist-info/LICENSE
flint_py-0.3.7.dist-info/WHEEL
flint_py.libs/libgmp-d797ad55.so.23.0.3
flint_py.libs/libflint-354fd9b1.so.13.5.2
flint_py.libs/libarb-c74e3e5c.so.2.8.0
flint_py.libs/libmpfr-e1af9faf.so.6.0.2
