Metadata-Version: 2.1
Name: flint-py
Version: 0.3.7
Summary: Repackage python-flint to include arb and flint as shared libraries
Home-page: https://gitlab.com/alisianoi/flint-py
Author: Fredrik Johansson
Author-email: fredrik.johansson@gmail.com
License: MIT
Platform: UNKNOWN
Classifier: Topic :: Scientific/Engineering :: Mathematics
License-File: LICENSE
